dist
types_boto3_accessanalyzer
types_boto3_account
types_boto3_acm
types_boto3_acm_pca
types_boto3_aiops
types_boto3_amp
types_boto3_amplify
types_boto3_amplifybackend
types_boto3_amplifyuibuilder
types_boto3_apigateway
types_boto3_apigatewaymanagementapi
types_boto3_apigatewayv2
types_boto3_appconfig
types_boto3_appconfigdata
types_boto3_appfabric
types_boto3_appflow
types_boto3_appintegrations
types_boto3_application_autoscaling
types_boto3_application_insights
types_boto3_application_signals
types_boto3_applicationcostprofiler
types_boto3_appmesh
types_boto3_apprunner
types_boto3_appstream
types_boto3_appsync
types_boto3_arc_region_switch
types_boto3_arc_zonal_shift
types_boto3_artifact
types_boto3_athena
types_boto3_auditmanager
types_boto3_autoscaling
types_boto3_autoscaling_plans
types_boto3_b2bi
types_boto3_backup
types_boto3_backup_gateway
types_boto3_backupsearch
types_boto3_batch
types_boto3_bcm_dashboards
types_boto3_bcm_data_exports
types_boto3_bcm_pricing_calculator
types_boto3_bcm_recommended_actions
types_boto3_bedrock
types_boto3_bedrock_agent
types_boto3_bedrock_agent_runtime
types_boto3_bedrock_agentcore
types_boto3_bedrock_agentcore_control
types_boto3_bedrock_data_automation
types_boto3_bedrock_data_automation_runtime
types_boto3_bedrock_runtime
types_boto3_billing
types_boto3_billingconductor
types_boto3_braket
types_boto3_budgets
types_boto3_ce
types_boto3_chatbot
types_boto3_chime
types_boto3_chime_sdk_identity
types_boto3_chime_sdk_media_pipelines
types_boto3_chime_sdk_meetings
types_boto3_chime_sdk_messaging
types_boto3_chime_sdk_voice
types_boto3_cleanrooms
types_boto3_cleanroomsml
types_boto3_cloud9
types_boto3_cloudcontrol
types_boto3_clouddirectory
types_boto3_cloudformation
types_boto3_cloudfront
types_boto3_cloudfront_keyvaluestore
types_boto3_cloudhsm
types_boto3_cloudhsmv2
types_boto3_cloudsearch
types_boto3_cloudsearchdomain
types_boto3_cloudtrail
types_boto3_cloudtrail_data
types_boto3_cloudwatch
types_boto3_codeartifact
